MPSPlots/__init__.py
MPSPlots/_version.py
MPSPlots/colormaps.py
MPSPlots/directories.py
MPSPlots/helper.py
MPSPlots/fonts/CMUSerif-Roman.sfd
MPSPlots/fonts/CMUSerif-Roman.ttf
MPSPlots/fonts/CMUSerif-Roman.ttf.sfd
MPSPlots/fonts/__init__.py
MPSPlots/fonts/cmu.serif-Roman-with-minus.ttf
MPSPlots/fonts/cmu.serif-bold.ttf
MPSPlots/fonts/cmu.serif-italic.ttf
MPSPlots/fonts/cmu.serif-roman.ttf
MPSPlots/styles/__init__.py
MPSPlots/styles/ggplot.mplstyle
MPSPlots/styles/mps_plot.mplstyle
MPSPlots/styles/new_age.mplstyle
mpsplots-1.8.5.dist-info/licenses/LICENSE
mpsplots-1.8.5.dist-info/METADATA
mpsplots-1.8.5.dist-info/WHEEL
mpsplots-1.8.5.dist-info/top_level.txt
mpsplots-1.8.5.dist-info/RECORD
