Metadata-Version: 2.4
Name: MPSPlots
Version: 1.8.5
Summary: A matplotlib wrapper for defered plots and plotting styles.
Author-email: Martin Poinsinet de Sivry-Houle <martin.poinsinet.de.sivry@gmail.com>
License: MIT License
Keywords: finit-difference,matrix
Classifier: Programming Language :: Python
Classifier: Programming Language :: Python :: 3
Classifier: Programming Language :: Python :: 3.11
Classifier: Programming Language :: Python :: 3.12
Classifier: Programming Language :: Python :: Implementation :: CPython
Classifier: Development Status :: 4 - Beta
Classifier: License :: OSI Approved :: MIT License
Requires-Python: >=3.8
License-File: LICENSE
Requires-Dist: matplotlib~=3.8
Requires-Dist: pyvista>=0.45.3
Provides-Extra: testing
Requires-Dist: pytest<9.0,>=7.4; extra == "testing"
Requires-Dist: pytest-cov<7,>=2; extra == "testing"
Requires-Dist: pytest-json-report~=1.5; extra == "testing"
Requires-Dist: coverage~=7.6; extra == "testing"
Provides-Extra: documentation
Requires-Dist: numpydoc==1.9.0; extra == "documentation"
Requires-Dist: sphinx>=5.1.1; extra == "documentation"
Requires-Dist: sphinx-gallery==0.19.0; extra == "documentation"
Requires-Dist: sphinx-rtd-theme==3.0.2; extra == "documentation"
Requires-Dist: pydata-sphinx-theme==0.16.1; extra == "documentation"
Provides-Extra: dev
Requires-Dist: flake8==7.1.1; extra == "dev"
Dynamic: license-file
